README.md
setup.cfg
setup.py
yargy2/__init__.py
yargy2/api.py
yargy2/check.py
yargy2/dot.py
yargy2/morph.py
yargy2/parser.py
yargy2/pipelines.py
yargy2/record.py
yargy2/span.py
yargy2/tagger.py
yargy2/token.py
yargy2/tokenizer.py
yargy2/visitor.py
yargy2.egg-info/PKG-INFO
yargy2.egg-info/SOURCES.txt
yargy2.egg-info/dependency_links.txt
yargy2.egg-info/requires.txt
yargy2.egg-info/top_level.txt
yargy2/interpretation/__init__.py
yargy2/interpretation/attribute.py
yargy2/interpretation/fact.py
yargy2/interpretation/interpretator.py
yargy2/interpretation/normalizer.py
yargy2/predicates/__init__.py
yargy2/predicates/bank.py
yargy2/predicates/constructors.py
yargy2/relations/__init__.py
yargy2/relations/bank.py
yargy2/relations/constructors.py
yargy2/relations/graph.py
yargy2/rule/__init__.py
yargy2/rule/bnf.py
yargy2/rule/constructors.py
yargy2/rule/transformators.py
yargy2/tree/__init__.py
yargy2/tree/constructors.py
yargy2/tree/transformators.py